{
  "data": {
    "allCount": 1285,
    "features": [
      {
        "attributes": {
          "OBJECTID": "1",
          "ID": "ecc9f2ba-f899-4adb-a86a-284d81bf2911",
          "LXDM": "G35",
          "LXMC": "济广高速",
          "QDMC": "南城东互通下行出口",
          "QDZH": "1228.5190000000",
          "QDPY": "0.0000000000",
          "ZDMC": "长链终点",
          "ZDZH": "1223.8980000000",
          "ZDPY": "0.0000000000",
          "LC": "4.6210000000",
          "YJND": "2010",
          "SXXFX": "2.0000000000",
          "DLLXBM": "0.0000000000",
          "DWMC": " ",
          "DRR": " "
        },
        "geometry": "LINESTRING (116.65963672 27.54180288, 116.66542667 27.58326667, 116.665435 27.58343667, 116.66544667 27.58377667, 116.66544667 27.58382465)",
        "geometryType": "MLineString"
      }
    ],
    "fields": [
      {
        "label": "",
        "name": "OBJECTID",
        "type": "INTEGER"
      },
      {
        "label": "",
        "name": "ID",
        "type": "NVARCHAR2"
      },
      {
        "label": "",
        "name": "LXDM",
        "type": "NVARCHAR2"
      },
      {
        "label": "",
        "name": "LXMC",
        "type": "NVARCHAR2"
      },
      {
        "label": "",
        "name": "QDMC",
        "type": "NVARCHAR2"
      },
      {
        "label": "",
        "name": "QDZH",
        "type": "NUMBER"
      },
      {
        "label": "",
        "name": "QDPY",
        "type": "NUMBER"
      },
      {
        "label": "",
        "name": "ZDMC",
        "type": "NVARCHAR2"
      },
      {
        "label": "",
        "name": "ZDZH",
        "type": "NUMBER"
      },
      {
        "label": "",
        "name": "ZDPY",
        "type": "NUMBER"
      },
      {
        "label": "",
        "name": "LC",
        "type": "NUMBER"
      },
      {
        "label": "",
        "name": "YJND",
        "type": "NVARCHAR2"
      },
      {
        "label": "",
        "name": "SXXFX",
        "type": "NUMBER"
      },
      {
        "label": "",
        "name": "DLLXBM",
        "type": "NUMBER"
      },
      {
        "label": "",
        "name": "DWMC",
        "type": "NVARCHAR2"
      },
      {
        "label": "",
        "name": "DRSJ",
        "type": "DATE"
      },
      {
        "label": "",
        "name": "DRR",
        "type": "NVARCHAR2"
      },
      {
        "label": "",
        "name": "SHAPE",
        "type": "ST_GEOMETRY"
      }
    ],
    "layerName": "GIS_LX",
    "max": false,
    "maxRecordCount": 1000
  },
  "success": true
}